achatbot/ChatTTS/setup.py
achatbot/ChatTTS/ChatTTS/__init__.py
achatbot/ChatTTS/ChatTTS/core.py
achatbot/ChatTTS/ChatTTS/norm.py
achatbot/ChatTTS/ChatTTS/config/__init__.py
achatbot/ChatTTS/ChatTTS/config/config.py
achatbot/ChatTTS/ChatTTS/model/__init__.py
achatbot/ChatTTS/ChatTTS/model/dvae.py
achatbot/ChatTTS/ChatTTS/model/gpt.py
achatbot/ChatTTS/ChatTTS/model/processors.py
achatbot/ChatTTS/ChatTTS/model/tokenizer.py
achatbot/ChatTTS/ChatTTS/model/cuda/__init__.py
achatbot/ChatTTS/ChatTTS/model/cuda/patch.py
achatbot/ChatTTS/ChatTTS/model/cuda/te_llama.py
achatbot/ChatTTS/ChatTTS/res/__init__.py
achatbot/ChatTTS/ChatTTS/utils/__init__.py
achatbot/ChatTTS/ChatTTS/utils/dl.py
achatbot/ChatTTS/ChatTTS/utils/gpu.py
achatbot/ChatTTS/ChatTTS/utils/io.py
achatbot/ChatTTS/ChatTTS/utils/log.py
achatbot/ChatTTS/examples/__init__.py
achatbot/ChatTTS/examples/api/client.py
achatbot/ChatTTS/examples/api/main.py
achatbot/ChatTTS/examples/cmd/run.py
achatbot/ChatTTS/examples/cmd/stream.py
achatbot/ChatTTS/examples/web/__init__.py
achatbot/ChatTTS/examples/web/ex.py
achatbot/ChatTTS/examples/web/funcs.py
achatbot/ChatTTS/examples/web/webui.py
achatbot/ChatTTS/tests/#511.py
achatbot/ChatTTS/tests/#588.py
achatbot/ChatTTS/tools/__init__.py
achatbot/ChatTTS/tools/audio/__init__.py
achatbot/ChatTTS/tools/audio/av.py
achatbot/ChatTTS/tools/audio/ffmpeg.py
achatbot/ChatTTS/tools/audio/np.py
achatbot/ChatTTS/tools/audio/pcm.py
achatbot/ChatTTS/tools/llm/__init__.py
achatbot/ChatTTS/tools/llm/llm.py
achatbot/ChatTTS/tools/logger/__init__.py
achatbot/ChatTTS/tools/logger/log.py
achatbot/ChatTTS/tools/normalizer/__init__.py
achatbot/ChatTTS/tools/normalizer/en.py
achatbot/ChatTTS/tools/normalizer/zh.py
achatbot/ChatTTS/tools/seeder/__init__.py
achatbot/ChatTTS/tools/seeder/ctx.py
achatbot/CosyVoice/webui.py
achatbot/CosyVoice/cosyvoice/__init__.py
achatbot/CosyVoice/cosyvoice/bin/average_model.py
achatbot/CosyVoice/cosyvoice/bin/export_jit.py
achatbot-0.0.9.post9.dist-info/licenses/LICENSE
achatbot-0.0.9.post9.dist-info/METADATA
achatbot-0.0.9.post9.dist-info/WHEEL
achatbot-0.0.9.post9.dist-info/top_level.txt
achatbot-0.0.9.post9.dist-info/RECORD
