Metadata-Version: 2.4
Name: achatbot
Version: 0.0.9.post9
Summary: An open source chat bot for voice (and multimodal) assistants
Author-email: weedge <weege007@gmail.com>
Maintainer-email: weedge <weege007@gmail.com>
License: BSD 3-Clause License
Project-URL: Homepage, https://github.com/ai-bot-pro/chat-bot
Project-URL: Documentation, https://github.com/ai-bot-pro/chat-bot/blob/main/docs
Project-URL: Repository, https://github.com/ai-bot-pro/chat-bot.git
Project-URL: Issues, https://github.com/ai-bot-pro/chat-bot/issues
Project-URL: Changelog, https://github.com/ai-bot-pro/chat-bot/blob/main/CHANGELOG.md
Keywords: ai,chat bot,audio,speech,video,image
Classifier: Development Status :: 4 - Beta
Classifier: Intended Audience :: Developers
Classifier: Topic :: Software Development :: Build Tools
Classifier: Topic :: Scientific/Engineering :: Artificial Intelligence
Classifier: Topic :: Multimedia :: Sound/Audio
Classifier: Topic :: Multimedia :: Video
Classifier: License :: OSI Approved :: BSD License
Classifier: Programming Language :: Python :: 3
Classifier: Programming Language :: Python :: 3.10
Classifier: Programming Language :: Python :: 3.11
Classifier: Programming Language :: Python :: 3.12
License-File: LICENSE
Requires-Dist: requests
Requires-Dist: apipeline~=0.1.32
Requires-Dist: python-dotenv
Requires-Dist: pydub
Requires-Dist: pillow
Requires-Dist: aiohttp
Requires-Dist: scipy
Requires-Dist: pyloudnorm
Requires-Dist: numpy>=1.22.0
Provides-Extra: pyee
Requires-Dist: pyee~=12.0.0; extra == "pyee"
Provides-Extra: conf
Requires-Dist: omegaconf~=2.3.0; extra == "conf"
Requires-Dist: hydra-core~=1.3.2; extra == "conf"
Provides-Extra: yaml
Requires-Dist: PyYAML~=6.0.2; extra == "yaml"
Provides-Extra: gdown
Requires-Dist: gdown==5.1.0; extra == "gdown"
Provides-Extra: matplotlib
Requires-Dist: matplotlib==3.7.5; extra == "matplotlib"
Provides-Extra: tensorrt
Requires-Dist: tensorrt~=10.4.0; extra == "tensorrt"
Provides-Extra: einops
Requires-Dist: einops~=0.8.0; extra == "einops"
Provides-Extra: flash-attn
Requires-Dist: flash-attn==2.5.6; extra == "flash-attn"
Provides-Extra: tiktoken
Requires-Dist: tiktoken~=0.7.0; extra == "tiktoken"
Provides-Extra: verovio
Requires-Dist: verovio~=4.3.1; extra == "verovio"
Provides-Extra: accelerate
Requires-Dist: accelerate~=0.28.0; extra == "accelerate"
Provides-Extra: opencv
Requires-Dist: opencv-python~=4.10.0.84; extra == "opencv"
Provides-Extra: librosa
Requires-Dist: librosa~=0.10.2.post1; extra == "librosa"
Provides-Extra: soundfile
Requires-Dist: soundfile~=0.12.1; extra == "soundfile"
Provides-Extra: diffusers
Requires-Dist: torch==2.4.1; extra == "diffusers"
Requires-Dist: torchvision==0.19.1; extra == "diffusers"
Requires-Dist: torchaudio==2.4.1; extra == "diffusers"
Requires-Dist: diffusers[torch]~=0.31.0; extra == "diffusers"
Provides-Extra: bitsandbytes
Requires-Dist: bitsandbytes~=0.44.1; extra == "bitsandbytes"
Provides-Extra: autoawq
Requires-Dist: autoawq; extra == "autoawq"
Provides-Extra: fastapi
Requires-Dist: fastapi~=0.112.0; extra == "fastapi"
Provides-Extra: websocket
Requires-Dist: websockets~=12.0; extra == "websocket"
Provides-Extra: fastapi-bot-server
Requires-Dist: fastapi~=0.112.0; extra == "fastapi-bot-server"
Requires-Dist: uvicorn~=0.30.6; extra == "fastapi-bot-server"
Provides-Extra: ngrok-proxy
Requires-Dist: pyngrok~=7.2.0; extra == "ngrok-proxy"
Requires-Dist: nest-asyncio~=1.6.0; extra == "ngrok-proxy"
Provides-Extra: agora
Requires-Dist: colorlog; extra == "agora"
Requires-Dist: agora-realtime-ai-api-v1~=0.0.3; extra == "agora"
Requires-Dist: agora_python_server_sdk_v1~=0.0.2; extra == "agora"
Requires-Dist: achatbot[opencv]; extra == "agora"
Provides-Extra: daily
Requires-Dist: daily-python~=0.11.0; extra == "daily"
Provides-Extra: livekit
Requires-Dist: livekit~=0.17.5; extra == "livekit"
Provides-Extra: livekit-api
Requires-Dist: livekit-api~=0.7.1; extra == "livekit-api"
Provides-Extra: google-ai
Requires-Dist: google-generativeai~=0.8.3; extra == "google-ai"
Provides-Extra: openai
Requires-Dist: openai~=1.54.1; extra == "openai"
Provides-Extra: together-ai
Requires-Dist: together~=1.3.3; extra == "together-ai"
Provides-Extra: litellm
Requires-Dist: litellm~=1.52.0; extra == "litellm"
Provides-Extra: grpc
Requires-Dist: grpcio>=1.65.1; extra == "grpc"
Provides-Extra: grpc-tools
Requires-Dist: grpcio-tools>=1.65.1; extra == "grpc-tools"
Provides-Extra: rpc
Requires-Dist: grpcio>=1.65.1; extra == "rpc"
Provides-Extra: redis
Requires-Dist: redis~=5.0.0; extra == "redis"
Provides-Extra: queue
Requires-Dist: achatbot[redis]; extra == "queue"
Provides-Extra: livekit-transport
Requires-Dist: achatbot[livekit,livekit-api]; extra == "livekit-transport"
Provides-Extra: daily-transport
Requires-Dist: achatbot[daily]; extra == "daily-transport"
Provides-Extra: websocket-server-transport
Requires-Dist: achatbot[websocket]; extra == "websocket-server-transport"
Provides-Extra: agora-transport
Requires-Dist: achatbot[agora]; extra == "agora-transport"
Provides-Extra: pyaudio-stream
Requires-Dist: PyAudio~=0.2.14; extra == "pyaudio-stream"
Provides-Extra: daily-room-audio-stream
Requires-Dist: achatbot[daily]; extra == "daily-room-audio-stream"
Provides-Extra: livekit-room-audio-stream
Requires-Dist: achatbot[livekit,livekit-api]; extra == "livekit-room-audio-stream"
Provides-Extra: agora-channel-audio-stream
Requires-Dist: achatbot[agora]; extra == "agora-channel-audio-stream"
Provides-Extra: speech-audio-stream
Requires-Dist: PyAudio~=0.2.14; extra == "speech-audio-stream"
Requires-Dist: daily-python~=0.11.0; extra == "speech-audio-stream"
Provides-Extra: porcupine-wakeword
Requires-Dist: pvporcupine~=3.0.2; extra == "porcupine-wakeword"
Provides-Extra: speech-waker
Requires-Dist: achatbot[porcupine_wakeword]; extra == "speech-waker"
Provides-Extra: pyannote-vad
Requires-Dist: pyannote.audio~=3.2.0; extra == "pyannote-vad"
Provides-Extra: webrtcvad
Requires-Dist: webrtcvad~=2.0.10; extra == "webrtcvad"
Provides-Extra: silero-vad
Requires-Dist: torch; extra == "silero-vad"
Requires-Dist: torchaudio; extra == "silero-vad"
Provides-Extra: webrtc-silero-vad
Requires-Dist: achatbot[silero_vad,webrtcvad]; extra == "webrtc-silero-vad"
Provides-Extra: speech-vad
Requires-Dist: achatbot[pyannote_vad,silero_vad,webrtcvad]; extra == "speech-vad"
Provides-Extra: daily-webrtc-vad-analyzer
Requires-Dist: achatbot[daily]; extra == "daily-webrtc-vad-analyzer"
Provides-Extra: silero-vad-analyzer
Requires-Dist: achatbot[silero_vad]; extra == "silero-vad-analyzer"
Provides-Extra: speech-vad-analyzer
Requires-Dist: achatbot[daily_webrtc_vad_analyzer,silero_vad_analyzer]; extra == "speech-vad-analyzer"
Provides-Extra: rms-recorder
Provides-Extra: vad-recorder
Requires-Dist: achatbot[speech_vad]; extra == "vad-recorder"
Provides-Extra: llama-cpp
Requires-Dist: llama-cpp-python~=0.2.82; extra == "llama-cpp"
Provides-Extra: llm-personalai-proxy
Requires-Dist: geocoder~=1.38.1; extra == "llm-personalai-proxy"
Provides-Extra: sglang
Requires-Dist: sglang[all]==0.4.4.post1; extra == "sglang"
Provides-Extra: vllm
Requires-Dist: vllm==0.7.3; extra == "vllm"
Provides-Extra: transformers
Requires-Dist: transformers[torch]; extra == "transformers"
Provides-Extra: trtllm
Requires-Dist: tensorrt-llm==0.17.0.post1; extra == "trtllm"
Provides-Extra: flashinfer-python
Requires-Dist: flashinfer-python==0.2.3; extra == "flashinfer-python"
Provides-Extra: llm-transformers-manual-vision
Requires-Dist: transformers~=4.50.3; extra == "llm-transformers-manual-vision"
Requires-Dist: qwen-vl-utils; extra == "llm-transformers-manual-vision"
Requires-Dist: av; extra == "llm-transformers-manual-vision"
Requires-Dist: torch~=2.2.2; extra == "llm-transformers-manual-vision"
Requires-Dist: torchaudio~=2.2.2; extra == "llm-transformers-manual-vision"
Requires-Dist: torchvision~=0.17.2; extra == "llm-transformers-manual-vision"
Provides-Extra: llm-transformers-manual-vision-qwen
Requires-Dist: achatbot[llm_transformers_manual_vision]; extra == "llm-transformers-manual-vision-qwen"
Provides-Extra: llm-transformers-manual-vision-llama
Requires-Dist: achatbot[llm_transformers_manual_vision]; extra == "llm-transformers-manual-vision-llama"
Provides-Extra: llm-transformers-manual-vision-molmo
Requires-Dist: achatbot[einops,llm_transformers_manual_vision]; extra == "llm-transformers-manual-vision-molmo"
Provides-Extra: vision-transformers-got-ocr
Requires-Dist: achatbot[accelerate,llm_transformers_manual_vision,tiktoken,verovio]; extra == "vision-transformers-got-ocr"
Provides-Extra: llm-transformers-manual-vision-img-janus
Requires-Dist: achatbot[accelerate,einops,llm_transformers_manual_vision]; extra == "llm-transformers-manual-vision-img-janus"
Requires-Dist: sentencepiece; extra == "llm-transformers-manual-vision-img-janus"
Requires-Dist: attrdict; extra == "llm-transformers-manual-vision-img-janus"
Requires-Dist: timm>=0.9.16; extra == "llm-transformers-manual-vision-img-janus"
Provides-Extra: llm-transformers-manual-vision-deepseekvl2
Requires-Dist: achatbot[accelerate,einops]; extra == "llm-transformers-manual-vision-deepseekvl2"
Requires-Dist: transformers==4.38.2; extra == "llm-transformers-manual-vision-deepseekvl2"
Requires-Dist: xformers>=0.0.21; extra == "llm-transformers-manual-vision-deepseekvl2"
Requires-Dist: sentencepiece; extra == "llm-transformers-manual-vision-deepseekvl2"
Requires-Dist: attrdict; extra == "llm-transformers-manual-vision-deepseekvl2"
Requires-Dist: timm>=0.9.16; extra == "llm-transformers-manual-vision-deepseekvl2"
Provides-Extra: llm-transformers-manual-vision-kimi
Requires-Dist: numpy==1.26.2; extra == "llm-transformers-manual-vision-kimi"
Requires-Dist: blobfile; extra == "llm-transformers-manual-vision-kimi"
Requires-Dist: achatbot[accelerate,llm_transformers_manual_vision,tiktoken]; extra == "llm-transformers-manual-vision-kimi"
Provides-Extra: llm-transformers-manual-voice
Requires-Dist: transformers~=4.45.2; extra == "llm-transformers-manual-voice"
Requires-Dist: torch~=2.2.2; extra == "llm-transformers-manual-voice"
Requires-Dist: torchaudio~=2.2.2; extra == "llm-transformers-manual-voice"
Provides-Extra: llm-transformers-manual-voice-glm
Requires-Dist: achatbot[conf,gdown,llm_transformers_manual_voice,matplotlib,tts_cosy_voice]; extra == "llm-transformers-manual-voice-glm"
Provides-Extra: llm-transformers-manual-voice-freeze-omni
Requires-Dist: achatbot[librosa,llm_transformers_manual_voice,soundfile,yaml]; extra == "llm-transformers-manual-voice-freeze-omni"
Provides-Extra: llm-transformers-manual-speech-llasa
Requires-Dist: achatbot[llm_transformers_manual_voice]; extra == "llm-transformers-manual-speech-llasa"
Provides-Extra: llm-transformers-manual-speech-spark
Requires-Dist: achatbot[llm_transformers_manual_voice]; extra == "llm-transformers-manual-speech-spark"
Provides-Extra: llm-transformers-manual-speech-llama
Requires-Dist: achatbot[llm_transformers_manual_voice]; extra == "llm-transformers-manual-speech-llama"
Provides-Extra: llm-transformers-manual-vision-voice-minicpmo
Requires-Dist: achatbot[accelerate,librosa,soundfile]; extra == "llm-transformers-manual-vision-voice-minicpmo"
Requires-Dist: torch~=2.2.2; extra == "llm-transformers-manual-vision-voice-minicpmo"
Requires-Dist: torchaudio~=2.2.2; extra == "llm-transformers-manual-vision-voice-minicpmo"
Requires-Dist: torchvision~=0.17.2; extra == "llm-transformers-manual-vision-voice-minicpmo"
Requires-Dist: transformers==4.44.2; extra == "llm-transformers-manual-vision-voice-minicpmo"
Requires-Dist: vector-quantize-pytorch~=1.18.5; extra == "llm-transformers-manual-vision-voice-minicpmo"
Requires-Dist: vocos~=0.1.0; extra == "llm-transformers-manual-vision-voice-minicpmo"
Requires-Dist: decord; extra == "llm-transformers-manual-vision-voice-minicpmo"
Requires-Dist: moviepy; extra == "llm-transformers-manual-vision-voice-minicpmo"
Provides-Extra: llm-transformers-manual-vision-voice-qwen
Requires-Dist: achatbot[accelerate,librosa,soundfile]; extra == "llm-transformers-manual-vision-voice-qwen"
Requires-Dist: torch~=2.6.0; extra == "llm-transformers-manual-vision-voice-qwen"
Requires-Dist: torchaudio~=2.6.0; extra == "llm-transformers-manual-vision-voice-qwen"
Requires-Dist: torchvision~=0.21.0; extra == "llm-transformers-manual-vision-voice-qwen"
Requires-Dist: numpy==1.26.2; extra == "llm-transformers-manual-vision-voice-qwen"
Requires-Dist: qwen-omni-utils[decord]; extra == "llm-transformers-manual-vision-voice-qwen"
Requires-Dist: torchdiffeq; extra == "llm-transformers-manual-vision-voice-qwen"
Requires-Dist: x_transformers; extra == "llm-transformers-manual-vision-voice-qwen"
Provides-Extra: core-llm
Requires-Dist: achatbot[llama_cpp,llm_personalai_proxy]; extra == "core-llm"
Provides-Extra: whisper-asr
Requires-Dist: openai-whisper; extra == "whisper-asr"
Provides-Extra: whisper-timestamped-asr
Requires-Dist: whisper-timestamped; extra == "whisper-timestamped-asr"
Provides-Extra: whisper-faster-asr
Requires-Dist: faster-whisper; extra == "whisper-faster-asr"
Provides-Extra: whisper-transformers-asr
Requires-Dist: transformers[torch]>=4.40.2; extra == "whisper-transformers-asr"
Provides-Extra: whisper-mlx-asr
Requires-Dist: mlx_whisper~=0.2.0; (sys_platform == "darwin" and platform_machine == "arm64") and extra == "whisper-mlx-asr"
Provides-Extra: whisper-groq-asr
Requires-Dist: groq~=0.9.0; extra == "whisper-groq-asr"
Provides-Extra: sense-voice-asr
Requires-Dist: torch; extra == "sense-voice-asr"
Requires-Dist: torchaudio; extra == "sense-voice-asr"
Requires-Dist: funasr; extra == "sense-voice-asr"
Requires-Dist: onnx; extra == "sense-voice-asr"
Requires-Dist: onnxconverter-common; extra == "sense-voice-asr"
Provides-Extra: speech-asr
Requires-Dist: achatbot[sense_voice_asr,whisper_asr,whisper_faster_asr,whisper_groq_asr,whisper_mlx_asr,whisper_timestamped_asr,whisper_transformers_asr]; extra == "speech-asr"
Provides-Extra: codec-transformers-mimi
Requires-Dist: transformers[torch]~=4.45.1; extra == "codec-transformers-mimi"
Provides-Extra: codec-moshi-mimi
Requires-Dist: moshi~=0.1.0; extra == "codec-moshi-mimi"
Provides-Extra: codec-xcodec2
Requires-Dist: xcodec2==0.1.3; extra == "codec-xcodec2"
Provides-Extra: codec-transformers-dac
Requires-Dist: transformers[torch]~=4.45.1; extra == "codec-transformers-dac"
Provides-Extra: codec-bitokenizer
Requires-Dist: einops==0.8.1; extra == "codec-bitokenizer"
Requires-Dist: einx==0.3.0; extra == "codec-bitokenizer"
Requires-Dist: numpy==2.2.3; extra == "codec-bitokenizer"
Requires-Dist: omegaconf==2.3.0; extra == "codec-bitokenizer"
Requires-Dist: packaging==24.2; extra == "codec-bitokenizer"
Requires-Dist: safetensors==0.5.2; extra == "codec-bitokenizer"
Requires-Dist: soundfile==0.12.1; extra == "codec-bitokenizer"
Requires-Dist: soxr==0.5.0.post1; extra == "codec-bitokenizer"
Requires-Dist: torch==2.5.1; extra == "codec-bitokenizer"
Requires-Dist: torchaudio==2.5.1; extra == "codec-bitokenizer"
Requires-Dist: torchvision==0.20.1; extra == "codec-bitokenizer"
Requires-Dist: transformers==4.46.2; extra == "codec-bitokenizer"
Provides-Extra: codec-snac
Requires-Dist: snac; extra == "codec-snac"
Provides-Extra: codec-wavtokenizer
Requires-Dist: numpy==1.23.5; extra == "codec-wavtokenizer"
Requires-Dist: encodec; extra == "codec-wavtokenizer"
Requires-Dist: pyyaml; extra == "codec-wavtokenizer"
Requires-Dist: huggingface_hub; extra == "codec-wavtokenizer"
Requires-Dist: achatbot[einops,librosa,matplotlib,soundfile]; extra == "codec-wavtokenizer"
Provides-Extra: tts-coqui
Requires-Dist: TTS~=0.22.0; extra == "tts-coqui"
Provides-Extra: tts-edge
Requires-Dist: edge-tts~=6.1.12; extra == "tts-edge"
Provides-Extra: tts-g
Requires-Dist: gTTS~=2.5.1; extra == "tts-g"
Provides-Extra: tts-pyttsx3
Requires-Dist: pyttsx3~=2.90; extra == "tts-pyttsx3"
Provides-Extra: tts-cosy-voice
Requires-Dist: torch~=2.2.2; extra == "tts-cosy-voice"
Requires-Dist: torchaudio~=2.2.2; extra == "tts-cosy-voice"
Requires-Dist: transformers~=4.40.2; extra == "tts-cosy-voice"
Requires-Dist: hyperpyyaml~=1.2.2; extra == "tts-cosy-voice"
Requires-Dist: onnxruntime~=1.18.1; extra == "tts-cosy-voice"
Requires-Dist: openai-whisper==20231117; extra == "tts-cosy-voice"
Requires-Dist: WeTextProcessing~=1.0.2; sys_platform == "linux" and extra == "tts-cosy-voice"
Requires-Dist: conformer~=0.3.2; extra == "tts-cosy-voice"
Requires-Dist: diffusers[torch]~=0.30.0; extra == "tts-cosy-voice"
Requires-Dist: lightning~=2.2.4; extra == "tts-cosy-voice"
Requires-Dist: wget~=3.2; extra == "tts-cosy-voice"
Requires-Dist: modelscope~=1.16.0; extra == "tts-cosy-voice"
Requires-Dist: achatbot[conf]; extra == "tts-cosy-voice"
Provides-Extra: tts-cosy-voice2
Requires-Dist: achatbot[tts_cosy_voice]; extra == "tts-cosy-voice2"
Provides-Extra: tts-chat
Requires-Dist: torch~=2.2.2; extra == "tts-chat"
Requires-Dist: vocos~=0.1.0; extra == "tts-chat"
Requires-Dist: pybase16384~=0.3.7; extra == "tts-chat"
Requires-Dist: vector_quantize_pytorch~=1.16.1; extra == "tts-chat"
Requires-Dist: pynini~=2.1.5; sys_platform == "linux" and extra == "tts-chat"
Requires-Dist: WeTextProcessing~=1.0.2; sys_platform == "linux" and extra == "tts-chat"
Requires-Dist: nemo_text_processing~=1.0.2; sys_platform == "linux" and extra == "tts-chat"
Requires-Dist: transformers~=4.40.2; extra == "tts-chat"
Provides-Extra: tts-f5
Requires-Dist: wandb; extra == "tts-f5"
Requires-Dist: ema_pytorch; extra == "tts-f5"
Requires-Dist: datasets; extra == "tts-f5"
Requires-Dist: accelerate>=0.33.0; extra == "tts-f5"
Requires-Dist: bitsandbytes>0.37.0; (platform_machine != "arm64" and platform_system != "Darwin") and extra == "tts-f5"
Requires-Dist: tomli; extra == "tts-f5"
Requires-Dist: cached_path; extra == "tts-f5"
Requires-Dist: click; extra == "tts-f5"
Requires-Dist: torch~=2.2.2; extra == "tts-f5"
Requires-Dist: torchaudio~=2.2.2; extra == "tts-f5"
Requires-Dist: matplotlib; extra == "tts-f5"
Requires-Dist: numpy<=1.26.4; extra == "tts-f5"
Requires-Dist: torchdiffeq; extra == "tts-f5"
Requires-Dist: jieba; extra == "tts-f5"
Requires-Dist: pypinyin; extra == "tts-f5"
Requires-Dist: achatbot[librosa,soundfile]; extra == "tts-f5"
Requires-Dist: transformers~=4.40.2; extra == "tts-f5"
Requires-Dist: x_transformers>=1.31.14; extra == "tts-f5"
Requires-Dist: vocos~=0.1.0; extra == "tts-f5"
Provides-Extra: tts-openvoicev2
Requires-Dist: achatbot[librosa,soundfile,whisper_faster_asr,whisper_timestamped_asr]; extra == "tts-openvoicev2"
Requires-Dist: wavmark==0.0.3; extra == "tts-openvoicev2"
Requires-Dist: eng_to_ipa~=0.0.2; extra == "tts-openvoicev2"
Requires-Dist: inflect~=7.0.0; extra == "tts-openvoicev2"
Requires-Dist: unidecode~=1.3.7; extra == "tts-openvoicev2"
Requires-Dist: jieba; extra == "tts-openvoicev2"
Requires-Dist: pypinyin; extra == "tts-openvoicev2"
Requires-Dist: cn2an; extra == "tts-openvoicev2"
Requires-Dist: langid; extra == "tts-openvoicev2"
Provides-Extra: tts-kokoro
Requires-Dist: torch~=2.2.2; extra == "tts-kokoro"
Requires-Dist: transformers~=4.40.2; extra == "tts-kokoro"
Requires-Dist: phonemizer; extra == "tts-kokoro"
Requires-Dist: munch; extra == "tts-kokoro"
Provides-Extra: tts-onnx-kokoro
Requires-Dist: kokoro-onnx~=0.2.5; extra == "tts-onnx-kokoro"
Provides-Extra: tts-fishspeech
Requires-Dist: torch~=2.3.1; extra == "tts-fishspeech"
Requires-Dist: torchaudio~=2.3.1; extra == "tts-fishspeech"
Requires-Dist: transformers~=4.40.2; extra == "tts-fishspeech"
Requires-Dist: natsort>=8.4.0; extra == "tts-fishspeech"
Requires-Dist: loguru>=0.6.0; extra == "tts-fishspeech"
Requires-Dist: rich>=13.5.3; extra == "tts-fishspeech"
Requires-Dist: vector_quantize_pytorch==1.14.24; extra == "tts-fishspeech"
Requires-Dist: loralib>=0.1.2; extra == "tts-fishspeech"
Requires-Dist: tiktoken>=0.8.0; extra == "tts-fishspeech"
Requires-Dist: pytorch-lightning~=2.4.0; extra == "tts-fishspeech"
Requires-Dist: lightning~=2.4.0; extra == "tts-fishspeech"
Requires-Dist: pyrootutils; extra == "tts-fishspeech"
Requires-Dist: achatbot[conf,einops,librosa]; extra == "tts-fishspeech"
Provides-Extra: tts-llasa
Requires-Dist: achatbot[codec_xcodec2]; extra == "tts-llasa"
Provides-Extra: tts-zonos
Requires-Dist: torch>=2.5.1; extra == "tts-zonos"
Requires-Dist: inflect>=7.5.0; extra == "tts-zonos"
Requires-Dist: kanjize>=1.5.0; extra == "tts-zonos"
Requires-Dist: phonemizer>=3.3.0; extra == "tts-zonos"
Requires-Dist: sudachidict-full>=20241021; extra == "tts-zonos"
Requires-Dist: sudachipy>=0.6.10; extra == "tts-zonos"
Requires-Dist: torchaudio>=2.5.1; extra == "tts-zonos"
Requires-Dist: transformers>=4.48.1; extra == "tts-zonos"
Requires-Dist: huggingface-hub>=0.28.1; extra == "tts-zonos"
Requires-Dist: achatbot[soundfile]; extra == "tts-zonos"
Provides-Extra: tts-zonos-hybrid
Requires-Dist: achatbot[tts_zonos]; extra == "tts-zonos-hybrid"
Requires-Dist: flash-attn>=2.7.3; extra == "tts-zonos-hybrid"
Requires-Dist: mamba-ssm>=2.2.4; extra == "tts-zonos-hybrid"
Requires-Dist: causal-conv1d>=1.5.0.post8; extra == "tts-zonos-hybrid"
Provides-Extra: tts-step
Requires-Dist: torch==2.3.1; extra == "tts-step"
Requires-Dist: torchaudio==2.3.1; extra == "tts-step"
Requires-Dist: torchvision==0.18.1; extra == "tts-step"
Requires-Dist: transformers==4.48.3; extra == "tts-step"
Requires-Dist: accelerate==1.3.0; extra == "tts-step"
Requires-Dist: openai-whisper==20231117; extra == "tts-step"
Requires-Dist: sox==1.5.0; extra == "tts-step"
Requires-Dist: modelscope; extra == "tts-step"
Requires-Dist: six==1.16.0; extra == "tts-step"
Requires-Dist: hyperpyyaml; extra == "tts-step"
Requires-Dist: conformer==0.3.2; extra == "tts-step"
Requires-Dist: diffusers; extra == "tts-step"
Requires-Dist: onnxruntime-gpu==1.20.1; extra == "tts-step"
Requires-Dist: sentencepiece; extra == "tts-step"
Requires-Dist: funasr>=1.1.3; extra == "tts-step"
Requires-Dist: protobuf==5.29.3; extra == "tts-step"
Requires-Dist: achatbot[conf,librosa]; extra == "tts-step"
Provides-Extra: tts-spark
Requires-Dist: achatbot[codec_bitokenizer]; extra == "tts-spark"
Provides-Extra: tts-generator-spark
Requires-Dist: achatbot[tts_spark]; extra == "tts-generator-spark"
Provides-Extra: tts-orpheus
Requires-Dist: achatbot[codec_snac]; extra == "tts-orpheus"
Requires-Dist: numpy==1.26.4; extra == "tts-orpheus"
Requires-Dist: torch==2.3.1; extra == "tts-orpheus"
Requires-Dist: torchaudio==2.3.1; extra == "tts-orpheus"
Requires-Dist: transformers==4.48.3; extra == "tts-orpheus"
Provides-Extra: tts-mega3
Requires-Dist: torch==2.3.1; extra == "tts-mega3"
Requires-Dist: torchaudio==2.3.1; extra == "tts-mega3"
Requires-Dist: transformers==4.49.0; extra == "tts-mega3"
Requires-Dist: WeTextProcessing==1.0.4.1; extra == "tts-mega3"
Requires-Dist: pyloudnorm==0.1.1; extra == "tts-mega3"
Requires-Dist: x-transformers==1.44.4; extra == "tts-mega3"
Requires-Dist: torchdiffeq==0.2.5; extra == "tts-mega3"
Requires-Dist: openai-whisper==20240930; extra == "tts-mega3"
Requires-Dist: langdetect; extra == "tts-mega3"
Requires-Dist: attrdict; extra == "tts-mega3"
Requires-Dist: setproctitle==1.3.3; extra == "tts-mega3"
Requires-Dist: achatbot[librosa]; extra == "tts-mega3"
Provides-Extra: speech-tts
Requires-Dist: achatbot[tts_chat,tts_coqui,tts_cosy_voice,tts_edge,tts_f5,tts_g,tts_kokoro,tts_openvoicev2,tts_pyttsx3]; extra == "speech-tts"
Provides-Extra: stream-player
Provides-Extra: vision-yolo-detector
Requires-Dist: ultralytics~=8.3.12; extra == "vision-yolo-detector"
Requires-Dist: supervision~=0.24.0; extra == "vision-yolo-detector"
Provides-Extra: pytube
Requires-Dist: pytube~=15.0.0; extra == "pytube"
Provides-Extra: deep-translator
Requires-Dist: deep_translator~=1.11.4; extra == "deep-translator"
Provides-Extra: ai-langchain-framework-processor
Requires-Dist: langchain~=0.3.9; extra == "ai-langchain-framework-processor"
Provides-Extra: ai-frameworks-processor
Requires-Dist: achatbot[ai_langchain_framework_processor]; extra == "ai-frameworks-processor"
Provides-Extra: deepgram-asr-processor
Requires-Dist: deepgram-sdk~=3.7.7; extra == "deepgram-asr-processor"
Provides-Extra: asr-processor
Requires-Dist: achatbot[deepgram_asr_processor,speech_asr]; extra == "asr-processor"
Provides-Extra: cartesia-tts-processor
Requires-Dist: websockets~=12.0; extra == "cartesia-tts-processor"
Provides-Extra: tts-processor
Requires-Dist: achatbot[cartesia_tts_processor,openai,speech_tts]; extra == "tts-processor"
Provides-Extra: openai-llm-processor
Requires-Dist: achatbot[openai]; extra == "openai-llm-processor"
Provides-Extra: google-llm-processor
Requires-Dist: achatbot[google_ai,openai]; extra == "google-llm-processor"
Provides-Extra: litellm-processor
Requires-Dist: achatbot[litellm,openai]; extra == "litellm-processor"
Provides-Extra: llm-processor
Requires-Dist: achatbot[google_llm_processor,litellm_processor,openai_llm_processor]; extra == "llm-processor"
Provides-Extra: img-processor
Requires-Dist: openai~=1.54.1; extra == "img-processor"
Provides-Extra: glm-voice-processor
Requires-Dist: achatbot[bitsandbytes,llm_transformers_manual_voice_glm]; extra == "glm-voice-processor"
Provides-Extra: freeze-omni-voice-processor
Requires-Dist: achatbot[llm_transformers_manual_voice_freeze_omni]; extra == "freeze-omni-voice-processor"
Provides-Extra: moshi-voice-processor
Requires-Dist: moshi~=0.2.1; extra == "moshi-voice-processor"
Provides-Extra: step-voice-processor
Requires-Dist: achatbot[tts_step]; extra == "step-voice-processor"
Provides-Extra: daily-rtvi-bot
Requires-Dist: achatbot[daily_transport,llm_processor,tts_edge,whisper_groq_asr]; extra == "daily-rtvi-bot"
Provides-Extra: langchain-openai-tidb-vector
Requires-Dist: achatbot[ai_langchain_framework_processor]; extra == "langchain-openai-tidb-vector"
Requires-Dist: langchain-text-splitters~=0.3.2; extra == "langchain-openai-tidb-vector"
Requires-Dist: langchain-openai~=0.2.11; extra == "langchain-openai-tidb-vector"
Requires-Dist: langchain-community~=0.3.9; extra == "langchain-openai-tidb-vector"
Requires-Dist: tidb-vector~=0.0.10; extra == "langchain-openai-tidb-vector"
Requires-Dist: pymysql~=1.1.1; extra == "langchain-openai-tidb-vector"
Provides-Extra: daily-langchain-rag-bot
Requires-Dist: achatbot[daily_transport,langchain_openai_tidb_vector,llm_processor,tts_edge,whisper_groq_asr]; extra == "daily-langchain-rag-bot"
Provides-Extra: local-terminal-chat-bot
Requires-Dist: tqdm>=4.66.0; extra == "local-terminal-chat-bot"
Requires-Dist: achatbot[core_llm,pyaudio_stream,speech_asr,speech_tts,speech_vad,speech_waker,stream_player]; extra == "local-terminal-chat-bot"
Provides-Extra: daily-webrtc-terminal-chat-bot
Requires-Dist: achatbot[core_llm,daily_room_audio_stream,speech_asr,speech_tts,speech_vad,speech_waker,stream_player]; extra == "daily-webrtc-terminal-chat-bot"
Provides-Extra: remote-queue-chat-bot-fe
Requires-Dist: achatbot[queue,speech_audio_stream,stream_player]; extra == "remote-queue-chat-bot-fe"
Provides-Extra: remote-queue-chat-bot-be-worker
Requires-Dist: achatbot[core_llm,queue,speech_asr,speech_tts,speech_vad,speech_waker]; extra == "remote-queue-chat-bot-be-worker"
Provides-Extra: remote-rpc-chat-bot-fe
Requires-Dist: achatbot[rpc,speech_audio_stream]; extra == "remote-rpc-chat-bot-fe"
Provides-Extra: remote-rpc-chat-bot-be-worker
Requires-Dist: achatbot[core_llm,rpc,speech_asr,speech_tts,speech_vad,speech_waker]; extra == "remote-rpc-chat-bot-be-worker"
Provides-Extra: remote-grpc-tts-client
Requires-Dist: achatbot[grpc,stream_player]; extra == "remote-grpc-tts-client"
Provides-Extra: remote-grpc-tts-server
Requires-Dist: achatbot[grpc,speech_tts]; extra == "remote-grpc-tts-server"
Provides-Extra: test
Requires-Dist: sentence_transformers~=3.0.0; extra == "test"
Requires-Dist: pytest~=8.3.2; extra == "test"
Requires-Dist: pytest-mock~=3.14.0; extra == "test"
Dynamic: license-file
